CHANGELOG.md
blocklib/__init__.py
blocklib/blocks_generator.py
blocklib/candidate_blocks_generator.py
blocklib/configuration.py
blocklib/encoding.py
blocklib/evaluation.py
blocklib/pprlindex.py
blocklib/pprllambdafold.py
blocklib/pprlpsig.py
blocklib/schemas/signature-config-schema.json
blocklib/signature_generator.py
blocklib/simmeasure.py
blocklib/stats.py
blocklib/utils.py
blocklib/validation/__init__.py
blocklib/validation/constrained_types.py
blocklib/validation/lambda_fold_validation.py
blocklib/validation/psig_validation.py
blocklib/validation/shared_blocking_config.py
blocklib-0.1.11.dist-info/LICENSE
blocklib-0.1.11.dist-info/METADATA
blocklib-0.1.11.dist-info/WHEEL
blocklib-0.1.11.dist-info/RECORD
