Metadata-Version: 2.1
Name: blocklib
Version: 0.1.11
Summary: A library for blocking in record linkage
Home-page: https://github.com/data61/blocklib
License: Apache-2.0
Author: Wilko Henecka
Author-email: wilkohenecka@gmx.net
Requires-Python: >=3.8,<3.12
Classifier: Intended Audience :: Developers
Classifier: License :: OSI Approved :: Apache Software License
Classifier: Operating System :: OS Independent
Classifier: Programming Language :: Python :: 3
Classifier: Programming Language :: Python :: 3.8
Classifier: Programming Language :: Python :: 3.9
Classifier: Programming Language :: Python :: 3.10
Classifier: Programming Language :: Python :: 3.11
Requires-Dist: jsonschema (>=3.1,<5.0)
Requires-Dist: metaphone (>=0.6,<0.7)
Requires-Dist: numpy (>=1.20.1,<2.0.0)
Requires-Dist: pydantic (>=1.10,<2.0)
Requires-Dist: tqdm (>=4.36.1,<5.0.0)
Requires-Dist: typing_extensions (>=3.7.4,<5.0.0)
Project-URL: Bug Tracker, https://github.com/data61/blocklib/issues
Project-URL: Documentation, https://blocklib.readthedocs.io/en/latest/
